latexify/__init__.py
latexify/admin.py
latexify/apps.py
latexify/models.py
latexify/settings.py
latexify/tests.py
latexify/views.py
latexify/migrations/__init__.py
latexify/static/latexify/css/latex.css
latexify/templates/latexify/latexify.html
latexify/templates/latexify/scripts.html
latexify/templates/latexify/stylesheets.html
latexify/templatetags/__init__.py
latexify/templatetags/latexify.py
django_latexify-0.3.dist-info/LICENSE
django_latexify-0.3.dist-info/METADATA
django_latexify-0.3.dist-info/WHEEL
django_latexify-0.3.dist-info/top_level.txt
django_latexify-0.3.dist-info/RECORD
